huaweicloudsdkbssintl/__init__.py
huaweicloudsdkbssintl/v2/__init__.py
huaweicloudsdkbssintl/v2/bssintl_async_client.py
huaweicloudsdkbssintl/v2/bssintl_client.py
huaweicloudsdkbssintl/v2/model/__init__.py
huaweicloudsdkbssintl/v2/model/account_balance_v3.py
huaweicloudsdkbssintl/v2/model/account_manager.py
huaweicloudsdkbssintl/v2/model/agent_pay_info_v2.py
huaweicloudsdkbssintl/v2/model/amount_infomation_v2.py
huaweicloudsdkbssintl/v2/model/apply_enterprise_realname_auths_req.py
huaweicloudsdkbssintl/v2/model/apply_individual_realname_auths_req.py
huaweicloudsdkbssintl/v2/model/auto_renewal_resources_req.py
huaweicloudsdkbssintl/v2/model/auto_renewal_resources_request.py
huaweicloudsdkbssintl/v2/model/auto_renewal_resources_response.py
huaweicloudsdkbssintl/v2/model/az_code_info.py
huaweicloudsdkbssintl/v2/model/bill_sum_record_info_v2.py
huaweicloudsdkbssintl/v2/model/budget_info.py
huaweicloudsdkbssintl/v2/model/budget_record_info.py
huaweicloudsdkbssintl/v2/model/cancel_auto_renewal_resources_request.py
huaweicloudsdkbssintl/v2/model/cancel_auto_renewal_resources_response.py
huaweicloudsdkbssintl/v2/model/cancel_customer_order_req.py
huaweicloudsdkbssintl/v2/model/cancel_customer_order_request.py
huaweicloudsdkbssintl/v2/model/cancel_customer_order_response.py
huaweicloudsdkbssintl/v2/model/cancel_resources_subscription_request.py
huaweicloudsdkbssintl/v2/model/cancel_resources_subscription_response.py
huaweicloudsdkbssintl/v2/model/change_enterprise_realname_authentication_request.py
huaweicloudsdkbssintl/v2/model/change_enterprise_realname_authentication_response.py
huaweicloudsdkbssintl/v2/model/change_enterprise_realname_auths_req.py
huaweicloudsdkbssintl/v2/model/check_subcustomer_user_req.py
huaweicloudsdkbssintl/v2/model/check_user_identity_request.py
huaweicloudsdkbssintl/v2/model/check_user_identity_response.py
huaweicloudsdkbssintl/v2/model/conversion.py
huaweicloudsdkbssintl/v2/model/cost.py
huaweicloudsdkbssintl/v2/model/cost_data_by_dimension.py
huaweicloudsdkbssintl-3.1.184.dist-info/METADATA
huaweicloudsdkbssintl-3.1.184.dist-info/WHEEL
huaweicloudsdkbssintl-3.1.184.dist-info/licenses/LICENSE
huaweicloudsdkbssintl-3.1.184.dist-info/RECORD
